data_processor/__init__.py
data_processor/__main__.py
data_processor/processor.py
data_processor_NovEf-0.9.9.9.9.dist-info/METADATA
data_processor_NovEf-0.9.9.9.9.dist-info/WHEEL
data_processor_NovEf-0.9.9.9.9.dist-info/top_level.txt
data_processor_NovEf-0.9.9.9.9.dist-info/RECORD
