Metadata-Version: 2.1
Name: data_processor_NovEf
Version: 0.9.9.9.9
Summary: Это data_processor, делай с ним че хочешь
Author: Novoselov Efim
Author-email: Novoselov Efim <myemail@example.com>
License: MIT
Requires-Python: >=3.10
Requires-Dist: requests>=2.25.1
Requires-Dist: numpy>=1.19.2
Requires-Dist: pandas>=2.2.3
Requires-Dist: csv>=1.0
